README.md
setup.py
cpflows/__init__.py
cpflows/distributions.py
cpflows/functional.py
cpflows/icnn.py
cpflows/logdet_estimators.py
cpflows/made.py
cpflows/multiscale_flow.py
cpflows/naf.py
cpflows/test_made.py
cpflows/utils.py
cpflows.egg-info/PKG-INFO
cpflows.egg-info/SOURCES.txt
cpflows.egg-info/dependency_links.txt
cpflows.egg-info/requires.txt
cpflows.egg-info/top_level.txt
cpflows/datasets/__init__.py
cpflows/datasets/bsds300.py
cpflows/datasets/gas.py
cpflows/datasets/hepmass.py
cpflows/datasets/miniboone.py
cpflows/datasets/power.py
cpflows/flows/__init__.py
cpflows/flows/coupling.py
cpflows/flows/cpflows.py
cpflows/flows/elemwise.py
cpflows/flows/flows.py
cpflows/sylvester/__init__.py
cpflows/sylvester/models/VAE.py
cpflows/sylvester/models/__init__.py
cpflows/sylvester/models/flows.py
cpflows/sylvester/models/layers.py
cpflows/sylvester/optimization/__init__.py
cpflows/sylvester/optimization/loss.py
cpflows/sylvester/optimization/training.py
cpflows/sylvester/utils/__init__.py
cpflows/sylvester/utils/distributions.py
cpflows/sylvester/utils/load_data.py
cpflows/sylvester/utils/log_likelihood.py
cpflows/sylvester/utils/plotting.py
cpflows/sylvester/utils/visual_evaluation.py