Metadata-Version: 1.0
Name: cpflows
Version: 0.1.0
Summary: Convex Potential Flows package
Home-page: UNKNOWN
Author: CWHuang
Author-email: UNKNOWN
License: UNKNOWN
Platform: UNKNOWN
